odoo10_addon_partner_contact_configuration-10.0.1.0.0-py2.7-nspkg.pth
odoo10_addon_partner_contact_configuration-10.0.1.0.0.dist-info/top_level.txt
odoo10_addon_partner_contact_configuration-10.0.1.0.0.dist-info/WHEEL
odoo10_addon_partner_contact_configuration-10.0.1.0.0.dist-info/RECORD
odoo10_addon_partner_contact_configuration-10.0.1.0.0.dist-info/metadata.json
odoo10_addon_partner_contact_configuration-10.0.1.0.0.dist-info/DESCRIPTION.rst
odoo10_addon_partner_contact_configuration-10.0.1.0.0.dist-info/METADATA
odoo10_addon_partner_contact_configuration-10.0.1.0.0.dist-info/namespace_packages.txt
odoo/addons/partner_contact_configuration/__manifest__.py
odoo/addons/partner_contact_configuration/__init__.py
odoo/addons/partner_contact_configuration/README.rst
odoo/addons/partner_contact_configuration/views/partner_contact.xml
odoo/addons/partner_contact_configuration/static/description/icon.png
